main.py
yytiny_mcp_weather_upload-0.1.2.dist-info/METADATA
yytiny_mcp_weather_upload-0.1.2.dist-info/WHEEL
yytiny_mcp_weather_upload-0.1.2.dist-info/entry_points.txt
yytiny_mcp_weather_upload-0.1.2.dist-info/top_level.txt
yytiny_mcp_weather_upload-0.1.2.dist-info/RECORD
